Metadata-Version: 2.4
Name: kdnmcp
Version: 1.0.4
Summary: 快递鸟MCP服务 - 提供快递物流查询的MCP协议服务
Project-URL: Homepage, https://github.com/kdniao/kdniao-mcp
Project-URL: Repository, https://github.com/kdniao/kdniao-mcp.git
Project-URL: Issues, https://github.com/kdniao/kdniao-mcp/issues
Project-URL: Documentation, https://github.com/kdniao/kdniao-mcp#readme
Author-email: KDNiao MCP Team <support@kdniao.com>
License-File: LICENSE
Keywords: express,kdniao,logistics,mcp,快递鸟,物流查询
Classifier: Development Status :: 4 - Beta
Classifier: Intended Audience :: Developers
Classifier: License :: OSI Approved :: MIT License
Classifier: Programming Language :: Python :: 3
Classifier: Programming Language :: Python :: 3.9
Classifier: Programming Language :: Python :: 3.10
Classifier: Programming Language :: Python :: 3.11
Classifier: Programming Language :: Python :: 3.12
Classifier: Topic :: Communications
Classifier: Topic :: Internet :: WWW/HTTP :: HTTP Servers
Classifier: Topic :: Software Development :: Libraries :: Python Modules
Requires-Python: >=3.9
Requires-Dist: anyio>=4.0.0
Requires-Dist: fastapi>=0.104.0
Requires-Dist: fastmcp>=0.15.0
Requires-Dist: httpx>=0.27.0
Requires-Dist: loguru>=0.7.0
Requires-Dist: orjson>=3.9.0
Requires-Dist: pydantic-settings>=2.0.0
Requires-Dist: pydantic>=2.5.0
Requires-Dist: python-dateutil>=2.8.0
Requires-Dist: python-dotenv>=1.0.0
Requires-Dist: uvicorn[standard]>=0.24.0
Provides-Extra: dev
Requires-Dist: black>=23.0.0; extra == 'dev'
Requires-Dist: flake8>=6.0.0; extra == 'dev'
Requires-Dist: mypy>=1.5.0; extra == 'dev'
Requires-Dist: pytest-asyncio>=0.21.0; extra == 'dev'
Requires-Dist: pytest>=7.4.0; extra == 'dev'
Provides-Extra: server
Requires-Dist: gunicorn>=21.2.0; extra == 'server'
